camminady_altair_theme/__init__.py
camminady_altair_theme/py.typed
camminady_altair_theme/theme.py
camminady_altair_theme-0.1.0.dist-info/METADATA
camminady_altair_theme-0.1.0.dist-info/WHEEL
camminady_altair_theme-0.1.0.dist-info/entry_points.txt
camminady_altair_theme-0.1.0.dist-info/licenses/LICENSE
camminady_altair_theme-0.1.0.dist-info/RECORD
