Metadata-Version: 2.4
Name: camminady_altair_theme
Version: 0.1.0
Author-email: Thomas Camminady <0milieux_member@icloud.com>
License-File: LICENSE
Requires-Python: >=3.11
Requires-Dist: altair>=6.0.0
